CHANGES.txt
CONTRIBUTORS.txt
MANIFEST.in
README.txt
setup.py
docs/LICENSE.GPL
docs/LICENSE.txt
src/ecreall/__init__.py
src/ecreall.helpers.upgrade.egg-info/PKG-INFO
src/ecreall.helpers.upgrade.egg-info/SOURCES.txt
src/ecreall.helpers.upgrade.egg-info/dependency_links.txt
src/ecreall.helpers.upgrade.egg-info/entry_points.txt
src/ecreall.helpers.upgrade.egg-info/namespace_packages.txt
src/ecreall.helpers.upgrade.egg-info/not-zip-safe
src/ecreall.helpers.upgrade.egg-info/requires.txt
src/ecreall.helpers.upgrade.egg-info/top_level.txt
src/ecreall/helpers/__init__.py
src/ecreall/helpers/upgrade/__init__.py
src/ecreall/helpers/upgrade/configure.zcml
src/ecreall/helpers/upgrade/interfaces.py
src/ecreall/helpers/upgrade/tool.py