Metadata-Version: 1.1
Name: ecreall.helpers.upgrade
Version: 1.1.2
Summary: Adapter tool with helpers for upgrade often used at ecreall
Home-page: http://svn.plone.org/svn/collective/
Author: UNKNOWN
Author-email: UNKNOWN
License: gpl
Platform: UNKNOWN
Classifier: Programming Language :: Python
